qt_jsonschema_form/__init__.py
qt_jsonschema_form/defaults.py
qt_jsonschema_form/form.py
qt_jsonschema_form/signal.py
qt_jsonschema_form/utils.py
qt_jsonschema_form/widgets.py
qt_jsonschema_form-1.0.0.dist-info/METADATA
qt_jsonschema_form-1.0.0.dist-info/WHEEL
qt_jsonschema_form-1.0.0.dist-info/licenses/LICENSE
qt_jsonschema_form-1.0.0.dist-info/RECORD
