Metadata-Version: 2.1
Name: qt-jsonschema-form
Version: 1.0.0
Summary: A tool to generate Qt forms from JSON Schema
Project-URL: Documentation, https://github.com/unknown/qt-jsonschema-form#readme
Project-URL: Issues, https://github.com/unknown/qt-jsonschema-form/issues
Project-URL: Source, https://github.com/unknown/qt-jsonschema-form
Author-email: Angus Hollands <goosey15@gmail.com>
License-Expression: MIT
License-File: LICENSE
Classifier: Development Status :: 4 - Beta
Classifier: Programming Language :: Python
Classifier: Programming Language :: Python :: 3.7
Classifier: Programming Language :: Python :: 3.8
Classifier: Programming Language :: Python :: 3.9
Classifier: Programming Language :: Python :: 3.10
Classifier: Programming Language :: Python :: 3.11
Classifier: Programming Language :: Python :: Implementation :: CPython
Classifier: Programming Language :: Python :: Implementation :: PyPy
Requires-Python: >=3.7
Requires-Dist: jsonschema>=4.0
Requires-Dist: qtpy>=2.3
